analyze/__init__.py
build/lib/analyze/__init__.py
build/lib/build/lib/analyze/__init__.py
build/lib/build/lib/build/lib/analyze/__init__.py
build/lib/build/lib/build/lib/build/lib/analyze/__init__.py
build/lib/build/lib/build/lib/build/lib/build/lib/analyze/__init__.py
build/lib/build/lib/build/lib/build/lib/build/lib/build/lib/analyze/__init__.py
build/lib/build/lib/build/lib/build/lib/build/lib/build/lib/build/lib/analyze/__init__.py
build/lib/build/lib/build/lib/build/lib/build/lib/build/lib/build/lib/build/lib/analyze/__init__.py
build/lib/build/lib/build/lib/build/lib/build/lib/build/lib/build/lib/build/lib/build/lib/analyze/__init__.py
build/lib/build/lib/build/lib/build/lib/build/lib/build/lib/build/lib/build/lib/docs/conf.py
build/lib/build/lib/build/lib/build/lib/build/lib/build/lib/build/lib/build/lib/docs/notebooks/gio.py
build/lib/build/lib/build/lib/build/lib/build/lib/build/lib/build/lib/build/lib/docs/notebooks/validator.py
build/lib/build/lib/build/lib/build/lib/build/lib/build/lib/build/lib/build/lib/st_lucas/__init__.py
build/lib/build/lib/build/lib/build/lib/build/lib/build/lib/build/lib/build/lib/st_lucas/exceptions.py
build/lib/build/lib/build/lib/build/lib/build/lib/build/lib/build/lib/build/lib/st_lucas/io.py
build/lib/build/lib/build/lib/build/lib/build/lib/build/lib/build/lib/build/lib/st_lucas/logger.py
build/lib/build/lib/build/lib/build/lib/build/lib/build/lib/build/lib/build/lib/st_lucas/logging.conf
build/lib/build/lib/build/lib/build/lib/build/lib/build/lib/build/lib/build/lib/st_lucas/request.py
build/lib/build/lib/build/lib/build/lib/build/lib/build/lib/build/lib/build/lib/st_lucas/analyze/__init__.py
build/lib/build/lib/build/lib/build/lib/build/lib/build/lib/build/lib/build/lib/st_lucas/analyze/lc1_codes.csv
build/lib/build/lib/build/lib/build/lib/build/lib/build/lib/build/lib/build/lib/st_lucas/analyze/nomenclature_translation/LUCAS_unique_lc1_lu1_combinations_ALL.csv
st_lucas-2.0.0.dist-info/licenses/LICENSE
st_lucas-2.0.0.dist-info/METADATA
st_lucas-2.0.0.dist-info/WHEEL
st_lucas-2.0.0.dist-info/top_level.txt
st_lucas-2.0.0.dist-info/RECORD
