Metadata-Version: 2.4
Name: st_lucas
Version: 2.0.0
Summary: ST_LUCAS Python package
Author-email: Martin Landa <martin.landa@fsv.cvut.cz>, Ondřej Pešek <ondrej.pesek@fsv.cvut.cz>, Tomáš Bouček <tomas.boucek@fsv.cvut.cz>, Lukáš Brodský <lukas.brodsky@natur.cuni.cz>
License: MIT
Project-URL: documentation, https://geoforall.fsv.cvut.cz/st_lucas/api/
Project-URL: repository, https://gitlab.com/geoharmonizer_inea/st_lucas/st_lucas-python-package
Requires-Python: >=3.9
License-File: LICENSE
Requires-Dist: geopandas>=0.8
Requires-Dist: OWSLib>=0.26
Requires-Dist: GDAL>=3.8
Dynamic: license-file
